{
  "host": "localhost",
  "port": 3030,
  "public": "./public/",
  "paginate": {
    "default": 10,
    "max": 50
  },
  "postgresql": {
    "client": "pg",
    "connection": "postgres://unicorn_user:magical_password@localhost:5432/rainbow_database"
  },
  "authentication": {
    "entity": "user",
    "service": "users",
    "secret": "xC83SmIi76qjmSl5DToN6WtpMWfNgmgk",
    "authStrategies": [
      "jwt",
      "local"
    ],
    "jwtOptions": {
      "header": {
        "typ": "access"
      },
      "audience": "https://yourdomain.com",
      "algorithm": "HS256",
      "expiresIn": "1d"
    },
    "local": {
      "usernameField": "email",
      "passwordField": "password"
    }
  }
}